<manager id='10'>
    <managerfname>Albus</managerfname>
    <managerlname>Dumbledore</managerlname>
    <phone>
        <phoneid>1</phoneid>
        <number>42589785</number>
    </phone>
    <clients>
        <client>
            <cid>1</cid>
            <clientfname>Harry</clientfname>
            <clientlname>Potter</clientlname>
            <birth>31/07/1980</birth>
            <document>21123456</document>
            <email>harrypotter@gmail.com</email>
        </client>
        <client>
            <cid>1</cid>
            <clientfname>Hermione</clientfname>
            <clientlname>Granger</clientlname>
            <birth>19/09/1979</birth>
            <document>22123456</document>
            <email>hermionegranger@gmail.com</email>
        </client>
        <client>
            <cid>1</cid>
            <clientfname>Ron</clientfname>
            <clientlname>Weasley</clientlname>
            <birth>01/03/1980</birth>
            <document>21153445</document>
            <email>ronweasley@gmail.com</email>
        </client>
    </clients>
    <accounts>
        <account>
            <aid>1</aid>
            <balance>1000000</balance>
            <cbu>123546789</cbu>
            <alias>butter.beer</alias>
        </account>
        <account>
            <aid>2</aid>
            <balance>1000000</balance>
            <cbu>123546789</cbu>
            <alias>butter.beer</alias>
        </account>
        <account>
            <aid>3</aid>
            <balance>1000000</balance>
            <cbu>123546789</cbu>
            <alias>butter.beer</alias>
        </account>
    </accounts>
    <username>wingardium-leviosa</username>
</manager>